acclaimbadge/__init__.py
acclaimbadge/acclaim_client.py
acclaimbadge/acclaimbadge.py
acclaimbadge/public/img/ribbon.png
acclaimbadge/static/README.txt
acclaimbadge/static/css/acclaimbadge.css
acclaimbadge/static/html/acclaimbadge-studio.html
acclaimbadge/static/html/acclaimbadge.html
acclaimbadge/static/js/src/acclaimbadge.js
acclaimbadge/static/js/vendor/vue.social-shares.min.js
acclaimbadge_xblock-1.3.1.dist-info/METADATA
acclaimbadge_xblock-1.3.1.dist-info/WHEEL
acclaimbadge_xblock-1.3.1.dist-info/entry_points.txt
acclaimbadge_xblock-1.3.1.dist-info/top_level.txt
acclaimbadge_xblock-1.3.1.dist-info/RECORD
